django_phone_login-1.1.3.dist-info/DESCRIPTION.rst
django_phone_login-1.1.3.dist-info/METADATA
django_phone_login-1.1.3.dist-info/RECORD
django_phone_login-1.1.3.dist-info/WHEEL
django_phone_login-1.1.3.dist-info/metadata.json
django_phone_login-1.1.3.dist-info/top_level.txt
phone_login/__init__.py
phone_login/admin.py
phone_login/apps.py
phone_login/models.py
phone_login/serializers.py
phone_login/tests.py
phone_login/urls.py
phone_login/utils.py
phone_login/views.py
phone_login/__pycache__/__init__.cpython-36.pyc
phone_login/__pycache__/models.cpython-36.pyc
phone_login/__pycache__/serializers.cpython-36.pyc
phone_login/__pycache__/urls.cpython-36.pyc
phone_login/__pycache__/utils.cpython-36.pyc
phone_login/__pycache__/views.cpython-36.pyc
phone_login/backends/__init__.py
phone_login/backends/phone_backend.py
phone_login/backends/__pycache__/__init__.cpython-36.pyc
phone_login/backends/__pycache__/phone_backend.cpython-36.pyc
phone_login/migrations/0001_initial.py
phone_login/migrations/__init__.py
phone_login/migrations/__pycache__/0001_initial.cpython-36.pyc
phone_login/migrations/__pycache__/__init__.cpython-36.pyc
phone_login/templates/otp_sms.txt
